zcrypto/__init__.py
zpy_ciphers_utils-0.0.1.dist-info/LICENSE
zpy_ciphers_utils-0.0.1.dist-info/METADATA
zpy_ciphers_utils-0.0.1.dist-info/WHEEL
zpy_ciphers_utils-0.0.1.dist-info/top_level.txt
zpy_ciphers_utils-0.0.1.dist-info/RECORD
